py_jsonl_loader/__init__.py
py_jsonl_loader-0.1.2.dist-info/WHEEL
py_jsonl_loader-0.1.2.dist-info/METADATA
py_jsonl_loader-0.1.2.dist-info/RECORD
