Metadata-Version: 2.1
Name: py-jsonl-loader
Version: 0.1.2
Summary: 
Author: Philip Huang
Author-email: p208p2002@gmail.com
Requires-Python: >=3.6,<4.0
Classifier: Programming Language :: Python :: 3
Classifier: Programming Language :: Python :: 3.10
Classifier: Programming Language :: Python :: 3.6
Classifier: Programming Language :: Python :: 3.7
Classifier: Programming Language :: Python :: 3.8
Classifier: Programming Language :: Python :: 3.9
Requires-Dist: loguru (>=0.6.0,<0.7.0)
